jhidatabricksenv/__init__.py
jhiDatabricksEnvironment-0.1.dist-info/LICENSE
jhiDatabricksEnvironment-0.1.dist-info/METADATA
jhiDatabricksEnvironment-0.1.dist-info/WHEEL
jhiDatabricksEnvironment-0.1.dist-info/top_level.txt
jhiDatabricksEnvironment-0.1.dist-info/RECORD
