Metadata-Version: 2.1
Name: jhiDatabricksEnvironment
Version: 0.1
Summary: JHI Databricks Environment package
Home-page: https://github.com/pypa/JHIDatabricksEnvironment
Author: Core Cloud Team
Author-email: CoreCloudPlatform@janushenderson.com
License: UNKNOWN
Project-URL: Bug Tracker, https://github.com/pypa/JHIDatabricksEnvironment/issues
Platform: UNKNOWN
Classifier: Programming Language :: Python :: 3
Classifier: License :: OSI Approved :: MIT License
Classifier: Operating System :: OS Independent
Requires-Python: >=3.6
